bulk_cli/__init__.py
bulk_cli/command.py
bulk_cli/configs/default.json
bulk_cli/configs/help.txt
bulk_cli/help.py
bulk_cli/init.py
bulk_cli/install.py
bulk_cli/main.py
bulk_cli/run.py
bulk_cli/uninstall.py
bulk_cli-0.1.0.dist-info/entry_points.txt
bulk_cli-0.1.0.dist-info/LICENSE
bulk_cli-0.1.0.dist-info/METADATA
bulk_cli-0.1.0.dist-info/WHEEL
bulk_cli-0.1.0.dist-info/RECORD
